LICENSE
README.md
setup.py
rover/VERSION
rover/__init__.py
rover/__main__.py
rover/args.py
rover/asdf.py
rover/config.py
rover/coverage.py
rover/daemon.py
rover/download.py
rover/help.py
rover/index.py
rover/ingest.py
rover/lock.py
rover/logs.py
rover/manager.py
rover/process.py
rover/report.py
rover/request.py
rover/retrieve.py
rover/retrieve_metadata.py
rover/scan.py
rover/sqlite.py
rover/subscribe.py
rover/summary.py
rover/utils.py
rover/web.py
rover/workers.py
rover.egg-info/PKG-INFO
rover.egg-info/SOURCES.txt
rover.egg-info/dependency_links.txt
rover.egg-info/entry_points.txt
rover.egg-info/requires.txt
rover.egg-info/top_level.txt
tests/__init__.py
tests/config.py
tests/coverage.py
tests/download.py
tests/index.py
tests/ingest.py
tests/logs.py
tests/retrieve.py
tests/test_utils.py
tests/utils.py