Metadata-Version: 2.1
Name: rover
Version: 1.0.6
Summary: Tool for the robust retrieval of seismic data
Home-page: https://earthscope.github.io/rover
Author: EarthScope
Author-email: software@earthscope.org
Classifier: Development Status :: 4 - Beta
Classifier: Environment :: Console
Classifier: Intended Audience :: Science/Research
Classifier: License :: OSI Approved :: GNU General Public License v3 (GPLv3)
Classifier: Operating System :: Unix
Classifier: Operating System :: MacOS
Classifier: Programming Language :: Python :: 2.7
Classifier: Programming Language :: Python :: 3.5
Classifier: Programming Language :: Python :: 3.6
Classifier: Programming Language :: Python :: 3.7
Requires-Python: >=2.7, !=3.0.*, !=3.1.*, !=3.2.*, !=3.3.*, <4
Provides-Extra: dev
Provides-Extra: mseedindex
License-File: LICENSE
